__init__.py
main.py
dbmpy-1.0.4.dist-info/METADATA
dbmpy-1.0.4.dist-info/WHEEL
dbmpy-1.0.4.dist-info/top_level.txt
dbmpy-1.0.4.dist-info/RECORD
