Metadata-Version: 2.1
Name: dbmpy
Version: 1.0.4
Summary: Open source python3 library to manage SQLite3 databases
Author-email: xLitus <xLitus@protestant.com>
Project-URL: Homepage, https://github.com/xLitus/dbmpy
Project-URL: Issues, https://github.com/xLitus/dbmpy/issues
Classifier: Programming Language :: Python :: 3
Classifier: License :: OSI Approved :: MIT License
Classifier: Operating System :: OS Independent
Requires-Python: >=3.8
